bball_strategies/__init__.py
bball_strategies-0.1.2.dist-info/METADATA
bball_strategies-0.1.2.dist-info/WHEEL
bball_strategies-0.1.2.dist-info/RECORD
